notificationhubs_rest_python/NotificationHub.py
notificationhubs_rest_python-1.0.2.dist-info/LICENSE
notificationhubs_rest_python-1.0.2.dist-info/METADATA
notificationhubs_rest_python-1.0.2.dist-info/WHEEL
notificationhubs_rest_python-1.0.2.dist-info/top_level.txt
notificationhubs_rest_python-1.0.2.dist-info/RECORD
