Metadata-Version: 2.1
Name: notificationhubs-rest-python
Version: 1.0.2
Summary: A Python library for sending notifications using Azure Notification Hubs REST API.
Home-page: https://github.com/panevo/notificationhubs-rest-python
Author: Karlo Krakan
Author-email: karlo.krakan@panevo.com
License: Apache-2.0 License
Classifier: Intended Audience :: Developers
Classifier: License :: OSI Approved :: Apache Software License
Classifier: Programming Language :: Python
Classifier: Programming Language :: Python :: 3.8
Classifier: Programming Language :: Python :: 3.9
Classifier: Programming Language :: Python :: 3.10
Classifier: Programming Language :: Python :: 3.11
Classifier: Programming Language :: Python :: 3.12
License-File: LICENSE
